limeprompt/__init__.py
limeprompt/core.py
limeprompt/exceptions.py
limeprompt/types.py
limeprompt/utils.py
limeprompt-0.2.3.dist-info/METADATA
limeprompt-0.2.3.dist-info/WHEEL
limeprompt-0.2.3.dist-info/RECORD
