Metadata-Version: 2.1
Name: limeprompt
Version: 0.2.3
Summary: Light weight prompting and parsing library for LLM models
Home-page: https://github.com/iam-abbas/limeprompt
License: MIT
Keywords: llm,prompt,ai,openai,anthropic
Author: Abbas J
Author-email: abbas@altair.so
Requires-Python: >=3.9,<4.0
Classifier: License :: OSI Approved :: MIT License
Classifier: Operating System :: OS Independent
Classifier: Programming Language :: Python :: 3
Classifier: Programming Language :: Python :: 3.9
Classifier: Programming Language :: Python :: 3.10
Classifier: Programming Language :: Python :: 3.11
Classifier: Programming Language :: Python :: 3.12
Requires-Dist: anthropic (>=0.34.2,<0.35.0)
Requires-Dist: openai (>=1.50.2,<2.0.0)
Requires-Dist: pydantic (>=2.9.2,<3.0.0)
Project-URL: Repository, https://github.com/iam-abbas/limeprompt
